doranet/__init__.py
doranet/datatypes.py
doranet/engine.py
doranet/filters.py
doranet/hooks.py
doranet/interfaces.py
doranet/metacalc.py
doranet/metadata.py
doranet/network.py
doranet/py.typed
doranet/strategies.py
doranet/utils.py
doranet/modules/__init__.py
doranet/modules/enzymatic/JN3604IMT_rules.tsv
doranet/modules/enzymatic/__init__.py
doranet/modules/enzymatic/all_cofactors.tsv
doranet/modules/enzymatic/generate_network.py
doranet/modules/post_processing/OpenSans-Regular.ttf
doranet/modules/post_processing/__init__.py
doranet/modules/post_processing/post_processing.py
doranet/modules/synthetic/Reaction_Smarts_Forward.py
doranet/modules/synthetic/Reaction_Smarts_Retro.py
doranet/modules/synthetic/__init__.py
doranet/modules/synthetic/_function_generation.py
doranet/modules/synthetic/generate_network.py
doranet-0.5.6a1.dist-info/METADATA
doranet-0.5.6a1.dist-info/WHEEL
doranet-0.5.6a1.dist-info/licenses/LICENSE
doranet-0.5.6a1.dist-info/RECORD
