Metadata-Version: 2.3
Name: doranet
Version: 0.5.6a1
Summary: Python package for generating and analyzing chemical reaction networks
Project-URL: Homepage, https://github.com/wsprague-nu/doranet
Project-URL: Issues, https://github.com/wsprague-nu/doranet/issues
Author-email: William Sprague <wsprague@u.northwestern.edu>, Quan Zhang <quanzhang@northwestern.edu>
License:                                  Apache License
License-File: LICENSE
Classifier: Development Status :: 2 - Pre-Alpha
Classifier: License :: OSI Approved :: Apache Software License
Classifier: Operating System :: OS Independent
Classifier: Programming Language :: Python :: 3
Requires-Python: >=3.10
Requires-Dist: ipython
Requires-Dist: matplotlib
Requires-Dist: networkx
Requires-Dist: numpy
Requires-Dist: pandas
Requires-Dist: pillow
Requires-Dist: pyarrow
Requires-Dist: pypdf
Requires-Dist: rdkit<=2023.9.5
Requires-Dist: scipy
Provides-Extra: dev
Requires-Dist: hatch; extra == 'dev'
Requires-Dist: mypy; extra == 'dev'
Requires-Dist: myst-parser; extra == 'dev'
Requires-Dist: numpydoc; extra == 'dev'
Requires-Dist: pytest; extra == 'dev'
Requires-Dist: ruff; extra == 'dev'
Requires-Dist: scalene; extra == 'dev'
Requires-Dist: snakeviz; extra == 'dev'
Requires-Dist: sphinx; extra == 'dev'
Requires-Dist: sphinx-rtd-theme; extra == 'dev'
Requires-Dist: sphinxcontrib-mermaid; extra == 'dev'
Provides-Extra: doc
Requires-Dist: myst-parser; extra == 'doc'
Requires-Dist: numpydoc; extra == 'doc'
Requires-Dist: sphinx; extra == 'doc'
Requires-Dist: sphinx-rtd-theme; extra == 'doc'
Requires-Dist: sphinxcontrib-mermaid; extra == 'doc'
Provides-Extra: draw
Requires-Dist: pygraphviz; extra == 'draw'
Provides-Extra: lint
Requires-Dist: mypy; extra == 'lint'
Requires-Dist: ruff; extra == 'lint'
Provides-Extra: profile
Requires-Dist: scalene; extra == 'profile'
Requires-Dist: snakeviz; extra == 'profile'
Provides-Extra: test
Requires-Dist: pytest; extra == 'test'
